<document xml:lang="smn" id="no_id"><header><title>Poostâ peht - kela.fi</title><genre code="admin"/><author><unknown/></author><translator><unknown/></translator><translated_from xml:lang="fin"/><year>2019</year><wordcount>80</wordcount><conversion_status type="standard"/><availability><license type="standard"/></availability><multilingual><language xml:lang="fin"/></multilingual><origFileName>https://www.kela.fi/poosta-peht</origFileName><metadata><uncomplete/></metadata><version>XSLtemplate $Revision: 187360 $; file-specific xsl  Revision; common.xsl  $Revision$; </version></header>
<body>
<p xml:lang="fin">Siirry sisältöön</p>
<p xml:lang="fin">Siirry etusivulle</p>
<p xml:lang="fin">Suomi  </p>
<list><p type="listitem" xml:lang="fin">På svenska </p>
<p type="listitem" xml:lang="fin">In English </p>
<p type="listitem" xml:lang="fin">Saameksi </p>
<p type="listitem" xml:lang="fin">Selkosuomeksi </p>
<p type="listitem" xml:lang="fin">Lättläst </p>
<p type="listitem" xml:lang="fin">Viittomakielellä </p>
<p type="listitem" xml:lang="fin">På teckenspråk </p>
<p type="listitem">Other languages </p>
</list><p xml:lang="fin">Hae</p>
<list><p type="listitem" xml:lang="fin">Saame /</p>
<p type="listitem">Anarâškielân /</p>
<p type="listitem">Äššigâspalvâlem /</p>
<p type="listitem">Poostâ peht /</p>
</list><p type="title">Jis tun ášástâl poostâ peht</p>
<p>Tun puávtáh uuccâđ torjuid luámáttuvâiguin, maid tun uážuh Kela siijđoin. Tun uážuh luámáttuvâid meid Kela toimâttuvâin. Täärhist ucâmušâst, ete moh lahtosijd tast kalgeh leđe fáárust.</p>
<p>Jis tun uusah torjuu luámáttuvváin, te vuolgât tom Kelan poostâ peht oovtâst lahtosijguin. Kela postâčujottâs lii</p>
<p>Kela PL 10 00056 KELA</p>
<p xml:lang="fin">© Kansaneläkelaitos</p>
</body></document>
