<document xml:lang="smn" id="no_id">
  <header>
    <title/>
    <genre code="admin"/>
    <author>
      <unknown/>
    </author>
    <wordcount>276</wordcount>
    <conversion_status type="standard"/>
    <availability>
      <free/>
    </availability>
    <multilingual/>
    <origFileName>http://www.samediggi.fi/index.php?option=com_docman&amp;task=doc_download&amp;gid=816&amp;Itemid=10</origFileName>
    <parallel_text location="kulttuuriavustusten_hakeminen.pdf" xml:lang="sme"/>
    <parallel_text location="kulttuuriavustusten_hakeminen.pdf" xml:lang="sms"/>
    <parallel_text location="kulttuuriavustusten_hakeminen.pdf" xml:lang="fin"/>
    <metadata>
      <uncomplete/>
    </metadata>
    <version>XSLtemplate $Revision: 139793 $; file-specific xsl  Revision; common.xsl  $Revision: 134027 $; </version>
  </header>
  <body>
    <p xml:lang="sme">KULTURDOARJAGIID OHCAN </p>
    <p xml:lang="sme">Jagi 2009 stáhta bušeahttaárvalusas lea evttohuvvon 205 000 euro</p>
    <p xml:lang="smj">SÁMEGIELAT KULTUVRRA OVDDIDEAPMÁI JA SÁMESERVVIID DOAIBMAMII</p>
    <p xml:lang="sme">Sámediggi almmuha ohcanláhkai doarjagiid, mat mieđihuvvojit dán mearreruđas. Doarjjaohcamušaid galgá doaimmahit kulturlávdegoddái maŋimustá 30. skábmamánu 2008 rádjai čujuhusain:; Sámediggi,  Kulturlávdegoddi,    PL  41,  99981  OHCEJOHKA.  Ohcanskoviid  ja lassedieđuid fidne kulturčállis tel. 010 839 3103 ja fáksa 010 839 3131 sihke šleađgapoastta bokte </p>
    <p xml:lang="sme">inker-anni.sara@samediggi.fi. Skoviid sáhttá maiddái čálihit Sámedikki internetsiidduin čujuhusas www.samediggi.fi</p>
    <p xml:lang="sme">Ohcejogas 24.10.2008      Sámediggi </p>
    <p xml:lang="fkv">KULTTUURTORJUI UUCCÂM </p>
    <p>Staatâ budjetist ive 2009 lii iävtuttum 205 000 eurod</p>
    <p>SÄMIKIELÂLÂŠ KULTTUUR OOVDEDMÂN JÁ SÄMISEERVIJ TOOIMÂN</p>
    <p>Sämitigge  almoot  taan  meriruuđâst  torjuid  uuccâmnáál.  Toorjâucâmušâid  kalga  toimâttiđ kulttuurlävdikoodán  majemustáá  30.  skammâmáánu  2008  räi čujottâssáin; Sämitigge, Kulttuurlävdikodde,  PL  41,  99801  UCJUUHÂ.  Uuccâmluámáttuvâid  já  lasetiäđuid  finnee kulttuurčällest puh.    já fax    sehe šleđgâpoostâst</p>
    <p>inker-anni.sara@samediggi.fi  Luámáttuvâid  puáhtá  meiddei  printtiđ  Sämitige  viermisiijđoin</p>
    <p>čujottâsâst www.samediggi.fi</p>
    <p>Ucjuuvâst 24.10.2008    Sämitigge </p>
    <p xml:lang="ger">KULTTUURVEÄŠKULTTUURVEÄŠKULTTUURVEÄŠKULTTUURVEÄŠǈǈTIEŠǆǆI OOCCMǈǈTIEŠǆǆI OOCCMǈǈTIEŠǆǆI OOCCMǈǈTIEŠǆǆI OOCCM’Š’Š’Š’Š</p>
    <p xml:lang="sms">Riikk eeŠjj 2009 budjeettest lij maadârdum 205 000 euŠrred</p>
    <p xml:lang="sms">SÄÄŠMǈI’LLSA KULTTUUR OOUDÂSVIIKKÂM DA SÄÄŠMSIEŠBRI TU’JJU</p>
    <p xml:lang="sms">SääŠmteŠǇǇ  ââlmad  tän  mieŠrrtieŠǇǇest  miõttum  veäŠǉǉtieŠǇǇid  ooččâmnalla.</p>
    <p xml:lang="sms">VeäŠǉǉtieŠǇǇooccmõõžžid  âlgg  vuõltteed  kulttuurvuŠvddkådda  mââimõõzzâst</p>
    <p xml:lang="sms">skamm’mannu  peeiŠv skamm’mannu  peeiŠv skamm’mannu  peeiŠv skamm’mannu  peeiŠv  mõõneeŠstmõõneeŠstmõõneeŠstmõõneeŠst addrõõzzin; SääŠmteŠǇǇ,</p>
    <p xml:lang="sms">KulttuurvuŠvddkåŠdd  PČ  41,  99981UTSJOKI.  Ooccâmblaaŋkid  da  lââŠssteâđaid</p>
    <p xml:lang="sms">vuäǏǏ  kulttuurpiisrest  tel.  010  839  3103  da  fakss  010 839  3131,  di  neŠttpååŠšt</p>
    <p xml:lang="sms">inker-anni.sara@samediggi.fi. Blaaŋk liâ še  interneeŠttest printteemnalla</p>
    <p xml:lang="sms">SääŠmteeŠǇǇi neŠttseeidâst addrõõzzâst www.samediggi.fi</p>
    <p xml:lang="sms">Uccjõõǅǅâšt 24.10.2008</p>
    <p xml:lang="sms">SääŠmteŠSääŠmteŠSääŠmteŠSääŠmteŠ    ǇǇǇǇǇǇǇǇ</p>
    <p xml:lang="sma">KULTTUURIAVUSTUSTEN HAKEMINEN </p>
    <p xml:lang="fin">Valtion vuoden 2009 talousarvioesityksessä on esitetty 205 000 euroa</p>
    <p xml:lang="sme">SAAMENKIELISEN KULTTUURIN EDISTÄMISEEN JA SAAMELAISJÄRJESTÖJEN TOIMINTAAN</p>
    <p xml:lang="fin">Saamelaiskäräjät julistaa tästä määrärahasta myönnettävät avustukset haettaviksi. Avustushakemukset  on  toimitettava  kulttuurilautakunnalle  viimeistään  30.  marraskuuta  2008 mennessä osoitteella; Saamelaiskäräjät,  Kulttuurilautakunta,  PL  41,    99981  UTSJOKI. Hakulomakkeita  ja  lisätietoja  saa  kulttuurisihteeriltä  puh.  010 839  3103  ja  fax  010  839  3131  sekä sähköpostitse inker-anni.sara@samediggi.fi. Lomakkeet ovat myös tulostettavissa Saamelaiskäräjien verkkosivuilta osoitteessa www.samediggi.fi.  </p>
    <p xml:lang="fin">Utsjoella 24.10.2008      Saamelaiskäräjät </p>
  </body>
</document>
