<document xml:lang="smn" id="no_id"><header><title/><genre code="admin"/><author><unknown/></author><wordcount>285</wordcount><conversion_status type="standard"/><availability><license type="standard"/></availability><multilingual/><metadata><uncomplete/></metadata><version>XSLtemplate $Revision$; file-specific xsl  Revision; common.xsl  $Revision$; </version></header><body><p xml:lang="sms"><em type="bold">SÁMEDIGGI </em></p>
<p xml:lang="vep"><em type="bold">ČUÁKKIMPOVDIITTÂS 1/2016 </em></p>
<p><em type="bold">SÄMITIGGE </em>11.2.2016 </p>
<p xml:lang="nno">Dno: /D.k.1/2016</p>
<p><em type="bold">SÄÄ´MTE´ĞĞ SAAMELAISKÄRÄJÄT </em>Toimâorgaan: <em type="bold">Sämitige čuákkim Äigi </em>ma 23. peeivi kuovâmáánu 2016 tme 10. <em type="bold">Saje </em></p>
<p>Solju, Sajos, Aanaar</p>
<p><em type="bold">Ääših kieđâvuššâmnáál </em>1 </p>
<p>Säämi suuvâ laavlâ 2</p>
<p>Čuákkim lekkâm: avestis puárásumos jeessân Kari Kyrö lekkâmsárnumvuáru 3</p>
<p>Čuákkim lavâlâšvuotâ já meridemváldálâšvuotâ 4</p>
<p>Pevdikirje tärhisteijei já jienâireknisteijei valjim 5</p>
<p>Olesáigásii saavâjođetteijee valjim toimâpajan 2016–2019 6</p>
<p>Eidusij čuákkimaašij kieđâvuššâmoornig tuhhiittem 7 § I värisaavâjođetteijee valjim toimâpajan 2016–2019 8 § II värisaavâjođetteijee valjim toimâpajan 2016–2019 9 § Stiivrâ asâttem toimâpajan 2016–2019 10 § Iäláttâs- já vuoigâdvuođâlävdikode asâttem toimâpajan 2016–2019 11 § Škovlim- já oppâmateriaallävdikode asâttem toimâpajan 2016–2019 12 § Kulttuurlävdikode asâttem toimâpajan 2016–2019 13 § Säämi kielârääđi asâttem toimâpajan 2016–2019 14 § Sosiaal- já tiervâsvuođâlävdikode asâttem toimâpajan 2016–2019 15 § Nuorâirääđi asâttem toimâpajan 2016–2017 16 § Tilitärhisteijee já suu väriulmuu valjim toimâpajan 2016 – 2019 17 § Jesânij já värijesânij nomâttem säämi parlamentaarlâš rááđán toimâpajan 2016 – 2019 18 § Sämmilij ovdâsteijee já suu väriulmui valjim kirholâščuákkimân čuávuvii neeljiivepajan 19 § Sämmilij škovlimaašij oovtâstpargo-orgaan asâttem já sämitige ovdâsteijei nomâttem toos toimâpajan 2016 – 2019 20 § Sämmilij sosiaal- já tiervâsvuođâaašij oovtâstpargo-orgaan asâttem já sämitige ovdâsteijei nomâttem toimâpajan 2016 – 2019 21 § Ohtsâštave-eennâmlâš sämikielâ áámmát- já reesuurskuávdáá Sámi Giellagáldu (Säämi Kielâkäldee) orjâlâš-, nuorttâlâš- já anarâškielâ kielâjuáhusij jesânij nomâttem toimâpajan 2016 – 2019 22 § Sämitige muštâluš staatârááđán ivveest 2015 23 § Vuolgâttâssavâstâllâm sämitige vaaljâpaje toimâm- já ruttâtuáluohjelmist 2016 - 2019 24 § Markkânistemhoovdâ virge vuáđudem 25 § Eres oovdân puáttee ääših 26 § Čuákkim joskâm</p>
<p>Čuákkim čuákánpuávdejeijee</p>
<p xml:lang="olo">Kari Kyrö</p>
<p>Haldâttâhhovdâ</p>
<p xml:lang="fin">Pia Ruotsala</p>
<p xml:lang="vep"><em type="bold">ČUÁKKIMÄIGITAVLU 23.2.2016 </em></p>
<p>TME 10.00 Čuákkim álgá (kähvifalâdem) 13.00</p>
<p>Purâdempuddâ, mon äigin jesânij já värijesânij kuvvim (juávkku- já persovnkuvvim) 15.00</p>
<p>Čuákkim juátkoo 21.00</p>
<p>Čuákkim nohá</p>
<p>Čuákkim juátkoo táárbu mield 24.2.2016 tme 9.00.</p>
<p>Kárvudât sämimááccuhân!</p>
</body></document>
